README.md
setup.cfg
setup.py
oidc_auth/__init__.py
oidc_auth/authentication.py
oidc_auth/settings.py
oidc_auth/util.py
wr_drf_oidc_auth.egg-info/PKG-INFO
wr_drf_oidc_auth.egg-info/SOURCES.txt
wr_drf_oidc_auth.egg-info/dependency_links.txt
wr_drf_oidc_auth.egg-info/requires.txt
wr_drf_oidc_auth.egg-info/top_level.txt